.gitignore
MANIFEST.in
README.rst
setup.cfg
setup.py
docs/HISTORY.rst
docs/LICENSE.GPL
docs/LICENSE.txt
docs/MANUAL.txt
raptus/__init__.py
raptus.article.core.egg-info/PKG-INFO
raptus.article.core.egg-info/SOURCES.txt
raptus.article.core.egg-info/dependency_links.txt
raptus.article.core.egg-info/entry_points.txt
raptus.article.core.egg-info/namespace_packages.txt
raptus.article.core.egg-info/not-zip-safe
raptus.article.core.egg-info/requires.txt
raptus.article.core.egg-info/top_level.txt
raptus/article/__init__.py
raptus/article/core/__init__.py
raptus/article/core/componentfilter.py
raptus/article/core/components.py
raptus/article/core/componentsdefault.py
raptus/article/core/componentselection.py
raptus/article/core/config.py
raptus/article/core/configure.zcml
raptus/article/core/event.py
raptus/article/core/interfaces.py
raptus/article/core/manageable.py
raptus/article/core/meta.zcml
raptus/article/core/overrides.zcml
raptus/article/core/permissions.zcml
raptus/article/core/setuphandlers.py
raptus/article/core/zcml.py
raptus/article/core/browser/__init__.py
raptus/article/core/browser/article_hide.png
raptus/article/core/browser/article_icon.gif
raptus/article/core/browser/article_show.png
raptus/article/core/browser/components.js
raptus/article/core/browser/components.pt
raptus/article/core/browser/components.py
raptus/article/core/browser/configure.zcml
raptus/article/core/browser/edit.py
raptus/article/core/browser/folderfactories.pt
raptus/article/core/browser/folderfactories.py
raptus/article/core/browser/manager.pt
raptus/article/core/browser/menu.py
raptus/article/core/browser/overrides.zcml
raptus/article/core/browser/related.gif
raptus/article/core/browser/related.pt
raptus/article/core/browser/related.py
raptus/article/core/browser/showhide.py
raptus/article/core/browser/toggle.pt
raptus/article/core/browser/view.pt
raptus/article/core/browser/view.py
raptus/article/core/content/__init__.py
raptus/article/core/content/article.py
raptus/article/core/content/configure.zcml
raptus/article/core/locales/plone.pot
raptus/article/core/locales/raptus.article.pot
raptus/article/core/locales/de/LC_MESSAGES/plone.mo
raptus/article/core/locales/de/LC_MESSAGES/plone.po
raptus/article/core/locales/de/LC_MESSAGES/raptus.article.mo
raptus/article/core/locales/de/LC_MESSAGES/raptus.article.po
