Metadata-Version: 1.1
Name: raptus.article.core
Version: 2.2
Summary: Provides a configurable article content type (replaces the default Page content type).
Home-page: https://github.com/Raptus/raptus.article.core
Author: Raptus AG
Author-email: dev@raptus.com
License: GPL
Platform: UNKNOWN
Classifier: Programming Language :: Python
Classifier: Topic :: Software Development :: Libraries :: Python Modules
